django_html_validator-0.5.0.dist-info/METADATA
django_html_validator-0.5.0.dist-info/RECORD
django_html_validator-0.5.0.dist-info/WHEEL
django_html_validator-0.5.0.dist-info/top_level.txt
htmlvalidator/__init__.py
htmlvalidator/client.py
htmlvalidator/core.py
htmlvalidator/exceptions.py
htmlvalidator/middleware.py
htmlvalidator/utils.py
