Metadata-Version: 2.1
Name: django-html-validator
Version: 0.5.0
Summary: Yo! Check your HTML!
Home-page: https://github.com/peterbe/django-html-validator
Author: Peter Bengtsson
Author-email: mail@peterbe.com
License: MPL v2.0
Platform: UNKNOWN
Classifier: Framework :: Django
Classifier: License :: OSI Approved :: Mozilla Public License 2.0 (MPL 2.0)
Classifier: Operating System :: OS Independent
Classifier: Framework :: Django
Classifier: Framework :: Django :: 1.8
Classifier: Framework :: Django :: 1.9
Classifier: Framework :: Django :: 1.10
Classifier: Programming Language :: Python
Classifier: Programming Language :: Python :: 2
Classifier: Programming Language :: Python :: 2.7
Classifier: Programming Language :: Python :: 3
Classifier: Programming Language :: Python :: 3.4
Classifier: Programming Language :: Python :: 3.5
Classifier: Topic :: Software Development :: Libraries :: Python Modules
Requires-Dist: requests
